README.md
setup.py
fincrux/__init__.py
fincrux/__version__.py
fincrux/api.py
fincrux.egg-info/PKG-INFO
fincrux.egg-info/SOURCES.txt
fincrux.egg-info/dependency_links.txt
fincrux.egg-info/requires.txt
fincrux.egg-info/top_level.txt